racetrack/__init__.py
racetrack/__main__.py
racetrack/_ipython.py
racetrack/console.py
racetrack/model.py
racetrack/svg.py
racetrack/tracks/__init__.py
racetrack/tracks/barto-big.track
racetrack/tracks/barto-small.track
racetrack/tracks/maze.track
racetrack/tracks/ring.track
racetrack/tracks/river-deadend-narrow.track
racetrack/tracks/tiny.track
racetrack-0.5.8.dist-info/entry_points.txt
racetrack-0.5.8.dist-info/WHEEL
racetrack-0.5.8.dist-info/METADATA
racetrack-0.5.8.dist-info/RECORD
